easydist/__init__.py
easydist/config.py
easydist/version.py
easydist/autoflow/__init__.py
easydist/autoflow/solver.py
easydist/jax/__init__.py
easydist/jax/api.py
easydist/jax/bridge.py
easydist/jax/device_mesh.py
easydist/jax/sharding_interpreter.py
easydist/jax/utils.py
easydist/metashard/__init__.py
easydist/metashard/annotation.py
easydist/metashard/combination.py
easydist/metashard/halo.py
easydist/metashard/metair.py
easydist/metashard/metaop.py
easydist/metashard/view_propagation.py
easydist/platform/__init__.py
easydist/platform/jax.py
easydist/platform/torch.py
easydist/platform/tvm.py
easydist/torch/__init__.py
easydist/torch/api.py
easydist/torch/bridge.py
easydist/torch/device_mesh.py
easydist/torch/mem_anaylize.py
easydist/torch/preset_propagation.py
easydist/torch/sharding_interpreter.py
easydist/torch/spmd_prop_rule.py
easydist/torch/utils.py
easydist/torch/experimental/__init__.py
easydist/torch/experimental/api.py
easydist/torch/experimental/compiler.py
easydist/torch/experimental/decomp_utils.py
easydist/torch/experimental/init_helper.py
easydist/torch/passes/__init__.py
easydist/torch/passes/eliminate_detach.py
easydist/torch/passes/fix_bias.py
easydist/torch/passes/fix_embedding.py
easydist/torch/passes/fix_meta_device.py
easydist/torch/passes/sharding.py
easydist/utils/__init__.py
easydist/utils/testing.py
easydist/utils/timer.py
pai_easydist-0.1.0.dist-info/LICENSE
pai_easydist-0.1.0.dist-info/METADATA
pai_easydist-0.1.0.dist-info/NOTICE
pai_easydist-0.1.0.dist-info/WHEEL
pai_easydist-0.1.0.dist-info/top_level.txt
pai_easydist-0.1.0.dist-info/RECORD
